realscreenPy/__init__.py
realscreenPy/main.py
realscreenPy-1.0.1.dist-info/LICENSE
realscreenPy-1.0.1.dist-info/METADATA
realscreenPy-1.0.1.dist-info/WHEEL
realscreenPy-1.0.1.dist-info/top_level.txt
realscreenPy-1.0.1.dist-info/RECORD
