Metadata-Version: 2.1
Name: realscreenPy
Version: 1.0.1
License-File: LICENSE
